{
  "users": [
    {
      "name": "Nguyễn Duy Thái",
      "phone": "091112983123",
      "id": "6cJTrc13P",
      "password": "iloveyou",
      "avatar": "uploads/edf762cc45971aac61be04200fc43f91"
    },
    {
      "name": "Nguyễn Duy Thái",
      "phone": "091112983123",
      "id": "CQa9gbUUs",
      "avatar": "uploads/016ab49b6863ca8cf8b4fed1ef5774b8"
    }
  ],
  "products": [
    {
      "id": "24caf707-3921-478e-87e8-5d62b5454d1d",
      "name": "Ventosanzap",
      "image": "https://www.instagram.com.limited/"
    },
    {
      "id": "8d8af033-2ada-4e91-b89b-123868877559",
      "name": "Vagram",
      "image": "https://www.instagram.com/.limited/"
    },
    {
      "id": "1ee5d1ee-c84f-4345-b312-a8f963a7cdde",
      "name": "Treeflex",
      "image": "https://www.instagram.com/.limited/"
    },
    {
      "id": "2fbef2d2-fc8b-46ca-898c-31b72de75e58",
      "name": "Zontrax",
      "image": "https://www.instagram.com/.limited/"
    },
    {
      "id": "12fecf7d-734b-4e39-b3f5-84f89b583644",
      "name": "Span",
      "image": "https://www.instagram.com/.limited/"
    },
    {
      "id": "fd8e19fc-11d0-4384-8e1d-93e062e14881",
      "name": "Toughjoyfax",
      "image": "https://www.instagram.com/.limited/"
    },
    {
      "id": "186b6655-ca0c-4619-af0a-85318d1e1136",
      "name": "Tampflex",
      "image": "https://www.instagram.com/.limited/"
    },
    {
      "id": "b0e1326b-545b-4dd9-9d8f-baedef9697bf",
      "name": "Andalax",
      "image": "https://www.instagram.com/.limited/"
    },
    {
      "id": "1c323f0e-abbd-43bb-ba85-e96b5e0835fe",
      "name": "Regrant",
      "image": "https://www.instagram.com/.limited/"
    },
    {
      "id": "3de14a60-17e8-436a-9ee5-1e91f3b7868f",
      "name": "Quo Lux",
      "image": "https://www.instagram.com/.limited/"
    },
    {
      "id": "99840c04-11e2-4dd5-8047-8630faf577f2",
      "name": "Lotlux",
      "image": "https://www.instagram.com/.limited/"
    },
    {
      "id": "f6f89ee0-f313-481b-9247-9eb49a53a893",
      "name": "Transcof",
      "image": "https://www.instagram.com/.limited/"
    },
    {
      "id": "72c577c0-874c-44a2-b50c-e0be9f7bbcde",
      "name": "Home Ing",
      "image": "https://www.instagram.com/.limited/"
    },
    {
      "id": "b3526249-ef1a-4784-9e23-d9ee3477a080",
      "name": "Tampflex",
      "image": "https://www.instagram.com/.limited/"
    },
    {
      "id": "e9b2ab91-64c2-4d66-be8d-9cdb9b02f5d1",
      "name": "Home Ing",
      "image": "https://www.instagram.com/.limited/"
    },
    {
      "id": "a77dc48c-2d17-4729-9206-54867c58e84b",
      "name": "Namfix",
      "image": "https://www.instagram.com/.limited/"
    },
    {
      "id": "683b7f95-936a-42e9-9afc-bc3fcb6e9044",
      "name": "Keylex",
      "image": "https://www.instagram.com/.limited/"
    },
    {
      "id": "6b37b9b5-f12e-4f95-8e37-41bbbc0bdbf0",
      "name": "Alphazap",
      "image": "https://www.instagram.com/.limited/"
    },
    {
      "id": "127fee5a-1d9a-4720-a9fb-14fa1523bec5",
      "name": "Domainer",
      "image": "https://www.instagram.com/.limited/"
    },
    {
      "id": "fbcbdf6a-e06c-4547-b29b-24110297616e",
      "name": "Bitchip",
      "image": "https://www.instagram.com/.limited/"
    },
    {
      "id": "ff5815fa-0f88-41f3-91af-b617bc6312b1",
      "name": "Alphazap",
      "image": "https://www.instagram.com/.limited/"
    },
    {
      "id": "b0c7fad3-8fc4-49ae-8f7a-f870aaa5df12",
      "name": "Temp",
      "image": "https://www.instagram.com/.limited/"
    },
    {
      "id": "97a33916-819e-4aa4-91bc-27c62f129adf",
      "name": "Quo Lux",
      "image": "https://www.instagram.com/.limited/"
    },
    {
      "id": "9c2cb80e-7e66-41a7-9fef-7823889551bc",
      "name": "Ronstring",
      "image": "https://www.instagram.com/.limited/"
    },
    {
      "id": "bc2ac2e7-72d1-4a30-8397-586ae291d1ad",
      "name": "Stringtough",
      "image": "https://www.instagram.com/.limited/"
    },
    {
      "id": "ebf4b588-14e7-4d9d-8c5f-95b3d8d2957e",
      "name": "Zamit",
      "image": "https://www.instagram.com/.limited/"
    },
    {
      "id": "0d4f6009-3e01-4cfd-9319-404d15ec8fc4",
      "name": "Redhold",
      "image": "https://www.instagram.com/.limited/"
    },
    {
      "id": "33444828-0010-449a-87d6-1982e79573da",
      "name": "Sub-Ex",
      "image": "https://www.instagram.com/.limited/"
    },
    {
      "id": "943f479e-cf62-4a13-a8f3-7d5cb073b243",
      "name": "Bamity",
      "image": "https://www.instagram.com/.limited/"
    },
    {
      "id": "67c00317-b21c-435a-8ba0-b6dfc4be92cc",
      "name": "Fix San",
      "image": "https://www.instagram.com/.limited/"
    },
    {
      "id": "3ba58259-f282-4b32-b256-a6e26aef5fcc",
      "name": "Sub-Ex",
      "image": "https://www.instagram.com/.limited/"
    },
    {
      "id": "5be44736-6094-45a7-8fab-fc9f44202229",
      "name": "Stringtough",
      "image": "https://www.instagram.com/.limited/"
    },
    {
      "id": "95ed624d-9c60-43a8-957e-ce287c8e843f",
      "name": "Tres-Zap",
      "image": "https://www.instagram.com/.limited/"
    },
    {
      "id": "84caf6c6-aaff-4d83-808c-46ab5f82754f",
      "name": "Latlux",
      "image": "https://www.instagram.com/.limited/"
    },
    {
      "id": "12866012-4a6e-4adf-8088-2352cf958788",
      "name": "Holdlamis",
      "image": "https://www.instagram.com/.limited/"
    },
    {
      "id": "a306996a-0bff-4136-90ff-d47ee2ec5c07",
      "name": "Voltsillam",
      "image": "https://www.instagram.com/.limited/"
    },
    {
      "id": "9e0a6693-c375-467c-b96a-c6bb972c7884",
      "name": "Bamity",
      "image": "https://www.instagram.com/.limited/"
    },
    {
      "id": "8650c980-bad3-4a46-a616-5e1033c57905",
      "name": "Treeflex",
      "image": "https://www.instagram.com/.limited/"
    },
    {
      "id": "e408a171-da00-43e7-91f5-b8bf3a63c5e0",
      "name": "Solarbreeze",
      "image": "https://www.instagram.com/.limited/"
    },
    {
      "id": "f4f9af05-18ab-47f6-8452-086627c56772",
      "name": "Vagram",
      "image": "https://www.instagram.com/.limited/"
    },
    {
      "id": "2b3d7154-e82b-4729-8c64-e0d706515004",
      "name": "Home Ing",
      "image": "https://www.instagram.com/.limited/"
    },
    {
      "id": "36fb2a00-87aa-4cce-acac-409264595724",
      "name": "Flowdesk",
      "image": "https://www.instagram.com/.limited/"
    },
    {
      "id": "4bba548c-c01c-49da-96bc-be50089543f9",
      "name": "Tin",
      "image": "https://www.instagram.com/.limited/"
    },
    {
      "id": "f4f910e4-771a-4672-bf46-4adc8147c752",
      "name": "Holdlamis",
      "image": "https://www.instagram.com/.limited/"
    },
    {
      "id": "48a45032-4661-4b7e-8bbb-3a12a9f71003",
      "name": "Viva",
      "image": "https://www.instagram.com/.limited/"
    },
    {
      "id": "d0de9171-72a2-496a-98e1-d098f7ed5ce1",
      "name": "Kanlam",
      "image": "https://www.instagram.com/.limited/"
    },
    {
      "id": "7fcb193a-62d5-474b-9121-e7a42d0f17a9",
      "name": "Span",
      "image": "https://www.instagram.com/.limited/"
    },
    {
      "id": "24aead9f-ef7a-4449-91a3-d159c5dc6874",
      "name": "Stringtough",
      "image": "https://www.instagram.com/.limited/"
    },
    {
      "id": "9eb7d5f0-3e65-482e-b604-f220bcac79d7",
      "name": "Fixflex",
      "image": "https://www.instagram.com/.limited/"
    },
    {
      "id": "ee4c95d3-4a70-4dcb-8bda-0d3717dcc083",
      "name": "Namfix",
      "image": "https://www.instagram.com/.limited/"
    },
    {
      "id": "5a018514-d548-40d6-9b0a-d7ae1a8ad7e2",
      "name": "Y-find",
      "image": "https://www.instagram.com/.limited/"
    },
    {
      "id": "d69818b0-e630-4122-acf3-b69b120bf8aa",
      "name": "Home Ing",
      "image": "https://www.instagram.com/.limited/"
    },
    {
      "id": "239a56ba-d41f-4e0d-bbb4-c5f448198688",
      "name": "Voltsillam",
      "image": "https://www.instagram.com/.limited/"
    },
    {
      "id": "194c1198-6fe7-4d84-a9fa-55a2543d00b1",
      "name": "Rank",
      "image": "https://www.instagram.com/.limited/"
    },
    {
      "id": "4d08fcc2-09a6-4f06-8ffc-37f1d806c005",
      "name": "Ronstring",
      "image": "https://www.instagram.com/.limited/"
    },
    {
      "id": "efd7142d-2002-4fca-8a0f-1f10287e5633",
      "name": "Otcom",
      "image": "https://www.instagram.com/.limited/"
    },
    {
      "id": "e0c4d0b0-fdeb-400a-8d25-cf0c4e0bea41",
      "name": "Treeflex",
      "image": "https://www.instagram.com/.limited/"
    },
    {
      "id": "650aaaea-aa42-4e13-a1e6-443961933c16",
      "name": "Zoolab",
      "image": "https://www.instagram.com/.limited/"
    },
    {
      "id": "b051eab4-1eae-47e4-8783-c7e1fef0ef7b",
      "name": "Ventosanzap",
      "image": "https://www.instagram.com/.limited/"
    },
    {
      "id": "eb328d81-14e2-4b93-a8f6-4ca33f3f2d31",
      "name": "Biodex",
      "image": "https://www.instagram.com/.limited/"
    },
    {
      "id": "17ca7f39-728a-478f-8afc-f04199578a1e",
      "name": "Zontrax",
      "image": "https://www.instagram.com/.limited/"
    },
    {
      "id": "881b2f46-017b-4d78-99fa-5178c18dbb61",
      "name": "Job",
      "image": "https://www.instagram.com/.limited/"
    },
    {
      "id": "7d7bf483-a145-4fff-90c6-2b8e089d81fe",
      "name": "It",
      "image": "https://www.instagram.com/.limited/"
    },
    {
      "id": "fb923bd7-56ec-4698-86c9-2fdeb0ad3a7e",
      "name": "Alphazap",
      "image": "https://www.instagram.com/.limited/"
    },
    {
      "id": "ae6dc346-ba2f-4a3c-b3b2-ff41a397c1a8",
      "name": "Sub-Ex",
      "image": "https://www.instagram.com/.limited/"
    },
    {
      "id": "c7423abc-e321-4c34-a1a3-8be5832cacd9",
      "name": "Toughjoyfax",
      "image": "https://www.instagram.com/.limited/"
    },
    {
      "id": "0cdf320d-c9f6-4133-9230-9b802c54ab43",
      "name": "Redhold",
      "image": "https://www.instagram.com/.limited/"
    },
    {
      "id": "1c70c89a-3960-4fb4-b077-4f14054cda02",
      "name": "Overhold",
      "image": "https://www.instagram.com/.limited/"
    },
    {
      "id": "e0e9bbe8-de5a-4571-bda0-1beaff6398ee",
      "name": "Wrapsafe",
      "image": "https://www.instagram.com/.limited/"
    },
    {
      "id": "e796dd1d-ec01-493c-9fc3-5baf7af1bea7",
      "name": "Stim",
      "image": "https://www.instagram.com/.limited/"
    },
    {
      "id": "1ebee345-62c0-4b5e-8c8e-9c545e83d3d3",
      "name": "Namfix",
      "image": "https://www.instagram.com/.limited/"
    },
    {
      "id": "c2005144-1fe2-479e-a33e-407622becf0a",
      "name": "Lotlux",
      "image": "https://www.instagram.com/.limited/"
    },
    {
      "id": "e8b59ebf-00d5-42e9-8032-88fb3473ae0d",
      "name": "Subin",
      "image": "https://www.instagram.com/.limited/"
    },
    {
      "id": "f12f9a21-9f4e-4984-9b5e-7234f37d4c47",
      "name": "Voyatouch",
      "image": "https://www.instagram.com/.limited/"
    },
    {
      "id": "f78da20e-9be5-4047-9446-d69d11051556",
      "name": "Zoolab",
      "image": "https://www.instagram.com/.limited/"
    },
    {
      "id": "f490d748-b831-47c3-98d7-57e6f972a57c",
      "name": "Toughjoyfax",
      "image": "https://www.instagram.com/.limited/"
    },
    {
      "id": "e7b453dc-bb11-4827-b4cf-d546f7a14746",
      "name": "It",
      "image": "https://www.instagram.com/.limited/"
    },
    {
      "id": "13a81ecf-c536-40f2-9a0e-640c12456f9c",
      "name": "Alpha",
      "image": "https://www.instagram.com/.limited/"
    },
    {
      "id": "400336a4-b79d-4d14-a6ee-f58d9537bf0e",
      "name": "Redhold",
      "image": "https://www.instagram.com/.limited/"
    },
    {
      "id": "d821bbbd-65bf-4d62-b5e4-a4df326f0118",
      "name": "Stringtough",
      "image": "https://www.instagram.com/.limited/"
    },
    {
      "id": "072d39e7-edad-4ddc-aa28-3e7d269ea3a6",
      "name": "Bigtax",
      "image": "https://www.instagram.com/.limited/"
    },
    {
      "id": "08ac0ace-088a-442c-9932-c6afa9ec769a",
      "name": "Zathin",
      "image": "https://www.instagram.com/.limited/"
    },
    {
      "id": "6eb189bf-8641-410e-a6ad-73c6088bf7d1",
      "name": "Bitchip",
      "image": "https://www.instagram.com/.limited/"
    },
    {
      "id": "8f50d0ea-63a0-4ece-8f43-558a2ef15188",
      "name": "Konklux",
      "image": "https://www.instagram.com/.limited/"
    },
    {
      "id": "93f33692-a59f-444f-9912-69f8ec5694b9",
      "name": "Temp",
      "image": "https://www.instagram.com/.limited/"
    },
    {
      "id": "2b59a1d3-daf5-41d2-8072-3b94bd77b667",
      "name": "Stronghold",
      "image": "https://www.instagram.com/.limited/"
    },
    {
      "id": "9da76f3c-7501-4b72-bb41-1542c365ce72",
      "name": "Lotstring",
      "image": "https://www.instagram.com/.limited/"
    },
    {
      "id": "9cf1fa8f-3cd4-48b1-aa75-dc902e4b976b",
      "name": "It",
      "image": "https://www.instagram.com/.limited/"
    },
    {
      "id": "2767e91f-ffe8-4680-823a-85a625e338e8",
      "name": "Treeflex",
      "image": "https://www.instagram.com/.limited/"
    },
    {
      "id": "0e77ecee-0274-4efd-b11c-d242395ff8be",
      "name": "Namfix",
      "image": "https://www.instagram.com/.limited/"
    },
    {
      "id": "acce3467-f5e3-474d-aae1-098af5f4322d",
      "name": "Alpha",
      "image": "https://www.instagram.com/.limited/"
    },
    {
      "id": "d93a0789-4b75-4f97-9caf-9fc8f4aa7b53",
      "name": "It",
      "image": "https://www.instagram.com/.limited/"
    },
    {
      "id": "251bd0d4-594a-4acb-8498-99c1aa869709",
      "name": "Fixflex",
      "image": "https://www.instagram.com/.limited/"
    },
    {
      "id": "95a5c08b-426d-435c-9b2d-c4f0800ff5fb",
      "name": "Flexidy",
      "image": "https://www.instagram.com/.limited/"
    },
    {
      "id": "1deb5552-2efb-4ca1-9d1a-631d77a6fab7",
      "name": "Flowdesk",
      "image": "https://www.instagram.com/.limited/"
    },
    {
      "id": "de625cca-57fe-4820-9a8f-17f1b9d26d01",
      "name": "Transcof",
      "image": "https://www.instagram.com/.limited/"
    },
    {
      "id": "7c507fc9-cbf7-4077-bf18-cd5b51c7fb8a",
      "name": "Temp",
      "image": "https://www.instagram.com/.limited/"
    },
    {
      "id": "6040cea6-2078-4251-8c69-d189df0215fa",
      "name": "Kanlam",
      "image": "https://www.instagram.com/.limited/"
    },
    {
      "id": "414e7589-c527-4e01-a379-f3cae3870a0b",
      "name": "Pannier",
      "image": "https://www.instagram.com/.limited/"
    },
    {
      "id": "197c6b5d-3d37-4c35-a251-ab770a61b271",
      "name": "Zontrax",
      "image": "https://www.instagram.com/.limited/"
    }
  ]
}